odoo/addons/remove_dup_acc_num_constraint/__init__.py
odoo/addons/remove_dup_acc_num_constraint/__manifest__.py
odoo/addons/remove_dup_acc_num_constraint/models/__init__.py
odoo/addons/remove_dup_acc_num_constraint/models/res_partner_bank.py
odoo12_addon_remove_dup_acc_num_constraint-12.0.1.0.1.dist-info/METADATA
odoo12_addon_remove_dup_acc_num_constraint-12.0.1.0.1.dist-info/WHEEL
odoo12_addon_remove_dup_acc_num_constraint-12.0.1.0.1.dist-info/top_level.txt
odoo12_addon_remove_dup_acc_num_constraint-12.0.1.0.1.dist-info/RECORD
